wink_sdk_notification/__init__.py
wink_sdk_notification/api_client.py
wink_sdk_notification/api_response.py
wink_sdk_notification/configuration.py
wink_sdk_notification/exceptions.py
wink_sdk_notification/py.typed
wink_sdk_notification/rest.py
wink_sdk_notification/api/__init__.py
wink_sdk_notification/api/notification_api.py
wink_sdk_notification/models/__init__.py
wink_sdk_notification/models/count_response_affiliate.py
wink_sdk_notification/models/generic_error_message.py
wink_sdk_notification/models/notification_affiliate.py
wink_sdk_notification/models/notification_view_affiliate.py
wink_sdk_notification/models/remove_entry_response_affiliate.py
wink_sdk_notification/models/show_notification400_response.py
wink_sdk_notification/models/show_notifications400_response.py
wink_sdk_notification-0.0.57.dist-info/licenses/LICENSE
wink_sdk_notification-0.0.57.dist-info/METADATA
wink_sdk_notification-0.0.57.dist-info/WHEEL
wink_sdk_notification-0.0.57.dist-info/top_level.txt
wink_sdk_notification-0.0.57.dist-info/RECORD
