Metadata-Version: 2.4
Name: wink_sdk_notification
Version: 0.0.57
Summary: Wink API
Home-page: https://github.com/wink-travel/wink-sdk-python.git
Author: Bjorn Harvold
Author-email: Bjorn Harvold <bjorn@wink.travel>
License:                                  Apache License
Keywords: OpenAPI,OpenAPI-Generator,Wink API
License-File: LICENSE
Dynamic: author
Dynamic: home-page
Dynamic: license-file
